Metadata-Version: 2.1
Name: GroupImages
Version: 0.1.3
Home-page: https://github.com/cramirezhe/GroupImages
Author: Carlos Ramirez
Author-email: c.eduardo.ramirez.h@gmail.com
Requires-Python: >=3.8.9
License-File: LICENSE
